pywmma/__init__.py
pywmma/kpath.py
pywmma-0.0.3.dist-info/METADATA
pywmma-0.0.3.dist-info/WHEEL
pywmma-0.0.3.dist-info/top_level.txt
pywmma-0.0.3.dist-info/zip-safe
pywmma-0.0.3.dist-info/RECORD
