Metadata-Version: 2.1
Name: pywmma
Version: 0.0.3
Summary: Python Wrapper On mma
Home-page: 
Author: xjq
Author-email: xjq701229@outlook.com
License: UNKNOWN
Platform: UNKNOWN
Classifier: Programming Language :: Python :: 3
Requires-Dist: wolframclient
